{
  "metadata": {
    "resultset": {
      "offset": 98600,
      "count": 154115,
      "limit": 100
    }
  },
  "results": [
    {
      "elevation": 283.2,
      "mindate": "2015-07-28",
      "maxdate": "2025-03-05",
      "latitude": 45.105154,
      "name": "DELLWOOD 0.5 NNW, MN US",
      "datacoverage": 0.9158,
      "id": "GHCND:US1MNWG0058",
      "elevationUnit": "METERS",
      "longitude": -92.972897
    },
    {
      "elevation": 267.6,
      "mindate": "2018-06-01",
      "maxdate": "2019-10-03",
      "latitude": 45.247547,
      "name": "SCANDIA 2.8 E, MN US",
      "datacoverage": 0.6875,
      "id": "GHCND:US1MNWG0060",
      "elevationUnit": "METERS",
      "longitude": -92.770003
    },
    {
      "elevation": 276.5,
      "mindate": "2018-05-25",
      "maxdate": "2024-11-20",
      "latitude": 45.27318,
      "name": "FOREST LAKE 1.4 N, MN US",
      "datacoverage": 0.44,
      "id": "GHCND:US1MNWG0062",
      "elevationUnit": "METERS",
      "longitude": -92.95328
    },
    {
      "elevation": 258.5,
      "mindate": "2018-04-04",
      "maxdate": "2024-08-30",
      "latitude": 45.0119919,
      "name": "BAYPORT 0.5 SW, MN US",
      "datacoverage": 0.0786,
      "id": "GHCND:US1MNWG0063",
      "elevationUnit": "METERS",
      "longitude": -92.7917715
    },
    {
      "elevation": 306.6,
      "mindate": "2018-08-01",
      "maxdate": "2025-03-07",
      "latitude": 45.04298,
      "name": "MAHTOMEDI 1.3 S, MN US",
      "datacoverage": 0.7578,
      "id": "GHCND:US1MNWG0066",
      "elevationUnit": "METERS",
      "longitude": -92.965671
    },
    {
      "elevation": 324.3,
      "mindate": "2019-05-14",
      "maxdate": "2025-03-07",
      "latitude": 44.98208,
      "name": "OAKDALE 0.4 S, MN US",
      "datacoverage": 0.9993,
      "id": "GHCND:US1MNWG0074",
      "elevationUnit": "METERS",
      "longitude": -92.9651
    },
    {
      "elevation": 321.3,
      "mindate": "2019-04-01",
      "maxdate": "2024-11-20",
      "latitude": 44.97441,
      "name": "OAKDALE 0.9 SSE, MN US",
      "datacoverage": 0.2115,
      "id": "GHCND:US1MNWG0075",
      "elevationUnit": "METERS",
      "longitude": -92.95999
    },
    {
      "elevation": 290.5,
      "mindate": "2020-03-22",
      "maxdate": "2024-12-20",
      "latitude": 45.115415,
      "name": "STILLWATER 4.2 NNE, MN US",
      "datacoverage": 0.8383,
      "id": "GHCND:US1MNWG0079",
      "elevationUnit": "METERS",
      "longitude": -92.806866
    },
    {
      "elevation": 282.5,
      "mindate": "2020-04-08",
      "maxdate": "2025-03-07",
      "latitude": 45.0485151,
      "name": "STILLWATER 0.8 SW, MN US",
      "datacoverage": 0.9657,
      "id": "GHCND:US1MNWG0080",
      "elevationUnit": "METERS",
      "longitude": -92.839234
    },
    {
      "elevation": 218.2,
      "mindate": "2020-05-23",
      "maxdate": "2023-08-23",
      "latitude": 44.923963,
      "name": "LAKELAND 1.8 S, MN US",
      "datacoverage": 0.5732,
      "id": "GHCND:US1MNWG0081",
      "elevationUnit": "METERS",
      "longitude": -92.766482
    },
    {
      "elevation": 292.9,
      "mindate": "2020-05-26",
      "maxdate": "2022-08-19",
      "latitude": 45.0702805,
      "name": "MAHTOMEDI 0.8 NE, MN US",
      "datacoverage": 0.6617,
      "id": "GHCND:US1MNWG0082",
      "elevationUnit": "METERS",
      "longitude": -92.9558175
    },
    {
      "elevation": 318.5,
      "mindate": "2020-06-07",
      "maxdate": "2021-12-03",
      "latitude": 44.92671,
      "name": "WOODBURY 1.8 NW, MN US",
      "datacoverage": 0.6202,
      "id": "GHCND:US1MNWG0083",
      "elevationUnit": "METERS",
      "longitude": -92.94287
    },
    {
      "elevation": 263.3,
      "mindate": "2020-04-23",
      "maxdate": "2023-10-30",
      "latitude": 44.979219,
      "name": "STILLWATER 5.7 SSE, MN US",
      "datacoverage": 0.4627,
      "id": "GHCND:US1MNWG0086",
      "elevationUnit": "METERS",
      "longitude": -92.7868835
    },
    {
      "elevation": 302.1,
      "mindate": "2020-04-16",
      "maxdate": "2025-03-07",
      "latitude": 44.9093,
      "name": "WOODBURY 0.3 NNW, MN US",
      "datacoverage": 0.9334,
      "id": "GHCND:US1MNWG0088",
      "elevationUnit": "METERS",
      "longitude": -92.92522
    },
    {
      "elevation": 278.9,
      "mindate": "2020-04-29",
      "maxdate": "2025-03-05",
      "latitude": 44.880437,
      "name": "WOODBURY 1.8 SSE, MN US",
      "datacoverage": 0.9819,
      "id": "GHCND:US1MNWG0091",
      "elevationUnit": "METERS",
      "longitude": -92.911206
    },
    {
      "elevation": 313.9,
      "mindate": "2020-07-10",
      "maxdate": "2024-12-31",
      "latitude": 44.954262,
      "name": "OAKDALE 2.4 SSE, MN US",
      "datacoverage": 0.827,
      "id": "GHCND:US1MNWG0093",
      "elevationUnit": "METERS",
      "longitude": -92.95237
    },
    {
      "elevation": 270.4,
      "mindate": "2021-04-14",
      "maxdate": "2023-10-13",
      "latitude": 45.131027,
      "name": "STILLWATER 6.1 NNE, MN US",
      "datacoverage": 0.1106,
      "id": "GHCND:US1MNWG0096",
      "elevationUnit": "METERS",
      "longitude": -92.7596788
    },
    {
      "elevation": 296.9,
      "mindate": "2021-03-17",
      "maxdate": "2025-03-07",
      "latitude": 45.029849,
      "name": "OAK PARK HEIGHTS 0.7 WSW, MN US",
      "datacoverage": 1,
      "id": "GHCND:US1MNWG0098",
      "elevationUnit": "METERS",
      "longitude": -92.823065
    },
    {
      "elevation": 295.7,
      "mindate": "2021-03-31",
      "maxdate": "2022-08-08",
      "latitude": 45.2546864,
      "name": "FOREST LAKE 0.6 W, MN US",
      "datacoverage": 0.7863,
      "id": "GHCND:US1MNWG0100",
      "elevationUnit": "METERS",
      "longitude": -92.9704935
    },
    {
      "elevation": 273.4,
      "mindate": "2021-03-26",
      "maxdate": "2025-03-06",
      "latitude": 45.051782,
      "name": "STILLWATER 1.1 WSW, MN US",
      "datacoverage": 0.387,
      "id": "GHCND:US1MNWG0104",
      "elevationUnit": "METERS",
      "longitude": -92.849147
    },
    {
      "elevation": 274.6,
      "mindate": "2021-04-01",
      "maxdate": "2022-12-20",
      "latitude": 45.074171,
      "name": "STILLWATER 1.5 NW, MN US",
      "datacoverage": 0.998,
      "id": "GHCND:US1MNWG0106",
      "elevationUnit": "METERS",
      "longitude": -92.84606
    },
    {
      "elevation": 278.9,
      "mindate": "2021-04-05",
      "maxdate": "2024-08-21",
      "latitude": 44.859179,
      "name": "COTTAGE GROVE 3.1 NNE, MN US",
      "datacoverage": 0.34,
      "id": "GHCND:US1MNWG0108",
      "elevationUnit": "METERS",
      "longitude": -92.912404
    },
    {
      "elevation": 301.8,
      "mindate": "2021-04-06",
      "maxdate": "2025-03-07",
      "latitude": 45.0594224,
      "name": "MAHTOMEDI 0.6 ESE, MN US",
      "datacoverage": 0.8282,
      "id": "GHCND:US1MNWG0112",
      "elevationUnit": "METERS",
      "longitude": -92.954521
    },
    {
      "elevation": 289.6,
      "mindate": "2002-04-26",
      "maxdate": "2025-03-02",
      "latitude": 45.22421,
      "name": "FOREST LAKE 2.9 SE, MN US",
      "datacoverage": 0.8674,
      "id": "GHCND:US1MNWG0120",
      "elevationUnit": "METERS",
      "longitude": -92.91683
    },
    {
      "elevation": 262.1,
      "mindate": "2019-06-22",
      "maxdate": "2025-01-14",
      "latitude": 45.04164,
      "name": "OAK PARK HEIGHTS 0.8 NE, MN US",
      "datacoverage": 0.4814,
      "id": "GHCND:US1MNWG0124",
      "elevationUnit": "METERS",
      "longitude": -92.79905
    },
    {
      "elevation": 216.1,
      "mindate": "2022-04-10",
      "maxdate": "2025-03-07",
      "latitude": 45.0157612206068,
      "name": "BAYPORT 0.2 ESE, MN US",
      "datacoverage": 0.9411,
      "id": "GHCND:US1MNWG0131",
      "elevationUnit": "METERS",
      "longitude": -92.7798168271697
    },
    {
      "elevation": 299.3,
      "mindate": "2022-04-06",
      "maxdate": "2024-11-26",
      "latitude": 44.898474,
      "name": "AFTON 0.4 SSE, MN US",
      "datacoverage": 0.6232,
      "id": "GHCND:US1MNWG0132",
      "elevationUnit": "METERS",
      "longitude": -92.814645
    },
    {
      "elevation": 302.1,
      "mindate": "2022-03-24",
      "maxdate": "2022-11-11",
      "latitude": 44.8942276,
      "name": "WOODBURY 1.7 WSW, MN US",
      "datacoverage": 0.998,
      "id": "GHCND:US1MNWG0133",
      "elevationUnit": "METERS",
      "longitude": -92.9544341
    },
    {
      "elevation": 313,
      "mindate": "2022-04-10",
      "maxdate": "2024-11-04",
      "latitude": 44.9311494,
      "name": "WOODBURY 2.2 NW, MN US",
      "datacoverage": 0.4436,
      "id": "GHCND:US1MNWG0135",
      "elevationUnit": "METERS",
      "longitude": -92.9495591
    },
    {
      "elevation": 276.5,
      "mindate": "2022-04-01",
      "maxdate": "2025-03-06",
      "latitude": 45.04685,
      "name": "STILLWATER 1.0 SE, MN US",
      "datacoverage": 0.8324,
      "id": "GHCND:US1MNWG0136",
      "elevationUnit": "METERS",
      "longitude": -92.81395
    },
    {
      "elevation": 294.1,
      "mindate": "2022-05-01",
      "maxdate": "2024-12-14",
      "latitude": 44.9439250238716,
      "name": "WOODBURY 2.7 N, MN US",
      "datacoverage": 0.6653,
      "id": "GHCND:US1MNWG0138",
      "elevationUnit": "METERS",
      "longitude": -92.9159134596538
    },
    {
      "elevation": 268.2,
      "mindate": "2022-04-13",
      "maxdate": "2023-10-27",
      "latitude": 45.038567,
      "name": "OAK PARK HEIGHTS 0.7 NE, MN US",
      "datacoverage": 0.5577,
      "id": "GHCND:US1MNWG0139",
      "elevationUnit": "METERS",
      "longitude": -92.799336
    },
    {
      "elevation": 247.2,
      "mindate": "2022-05-01",
      "maxdate": "2025-03-07",
      "latitude": 44.8198,
      "name": "COTTAGE GROVE 0.3 NNE, MN US",
      "datacoverage": 0.4923,
      "id": "GHCND:US1MNWG0140",
      "elevationUnit": "METERS",
      "longitude": -92.925
    },
    {
      "elevation": 257.9,
      "mindate": "2022-05-06",
      "maxdate": "2024-11-22",
      "latitude": 45.153105,
      "name": "STILLWATER 7.4 NNE, MN US",
      "datacoverage": 0.4324,
      "id": "GHCND:US1MNWG0141",
      "elevationUnit": "METERS",
      "longitude": -92.76447
    },
    {
      "elevation": 298.7,
      "mindate": "2022-06-19",
      "maxdate": "2025-03-05",
      "latitude": 45.128735,
      "name": "HUGO 3.1 SSE, MN US",
      "datacoverage": 0.1706,
      "id": "GHCND:US1MNWG0143",
      "elevationUnit": "METERS",
      "longitude": -92.924825
    },
    {
      "elevation": 279.5,
      "mindate": "2022-08-23",
      "maxdate": "2024-11-01",
      "latitude": 44.997114,
      "name": "LAKE ELMO 1.8 E, MN US",
      "datacoverage": 0.2743,
      "id": "GHCND:US1MNWG0144",
      "elevationUnit": "METERS",
      "longitude": -92.865553
    },
    {
      "elevation": 286.8,
      "mindate": "2023-06-12",
      "maxdate": "2024-12-14",
      "latitude": 45.00991,
      "name": "LAKE ELMO 1.6 NE, MN US",
      "datacoverage": 0.6884,
      "id": "GHCND:US1MNWG0146",
      "elevationUnit": "METERS",
      "longitude": -92.87855
    },
    {
      "elevation": 290.2,
      "mindate": "2020-07-21",
      "maxdate": "2025-03-04",
      "latitude": 45.1615311,
      "name": "HUGO 1.1 WSW, MN US",
      "datacoverage": 1,
      "id": "GHCND:US1MNWG0157",
      "elevationUnit": "METERS",
      "longitude": -92.9808928
    },
    {
      "elevation": 238,
      "mindate": "2023-04-12",
      "maxdate": "2024-08-30",
      "latitude": 44.826375,
      "name": "SAINT PAUL PARK 0.8 SSE, MN US",
      "datacoverage": 1,
      "id": "GHCND:US1MNWG0158",
      "elevationUnit": "METERS",
      "longitude": -92.985981
    },
    {
      "elevation": 287.1,
      "mindate": "2023-06-22",
      "maxdate": "2024-11-01",
      "latitude": 45.256774,
      "name": "FOREST LAKE 1.5 E, MN US",
      "datacoverage": 0.4589,
      "id": "GHCND:US1MNWG0159",
      "elevationUnit": "METERS",
      "longitude": -92.928591
    },
    {
      "elevation": 296.9,
      "mindate": "2023-03-25",
      "maxdate": "2025-03-04",
      "latitude": 45.1805,
      "name": "MARINE ON SAINT CROIX 3.5 WSW, MN US",
      "datacoverage": 0.5584,
      "id": "GHCND:US1MNWG0160",
      "elevationUnit": "METERS",
      "longitude": -92.847
    },
    {
      "elevation": 282.9,
      "mindate": "2023-05-27",
      "maxdate": "2024-08-28",
      "latitude": 45.0515334121703,
      "name": "STILLWATER 0.8 WSW, MN US",
      "datacoverage": 0.2283,
      "id": "GHCND:US1MNWG0161",
      "elevationUnit": "METERS",
      "longitude": -92.8434023018239
    },
    {
      "elevation": 247.5,
      "mindate": "2023-05-19",
      "maxdate": "2024-11-20",
      "latitude": 45.21303,
      "name": "MARINE ON SAINT CROIX 1.2 NNE, MN US",
      "datacoverage": 0.2011,
      "id": "GHCND:US1MNWG0162",
      "elevationUnit": "METERS",
      "longitude": -92.767537
    },
    {
      "elevation": 291.1,
      "mindate": "2023-03-13",
      "maxdate": "2025-03-05",
      "latitude": 45.195,
      "name": "MARINE ON SAINT CROIX 3.3 W, MN US",
      "datacoverage": 0.7417,
      "id": "GHCND:US1MNWG0163",
      "elevationUnit": "METERS",
      "longitude": -92.848
    },
    {
      "elevation": 270.4,
      "mindate": "2021-06-02",
      "maxdate": "2024-08-01",
      "latitude": 45.0478548,
      "name": "STILLWATER 1.4 ESE, MN US",
      "datacoverage": 0.4543,
      "id": "GHCND:US1MNWG0164",
      "elevationUnit": "METERS",
      "longitude": -92.8022007
    },
    {
      "elevation": 290.5,
      "mindate": "2020-05-04",
      "maxdate": "2025-03-07",
      "latitude": 44.87457,
      "name": "WOODBURY 3.3 SW, MN US",
      "datacoverage": 0.7723,
      "id": "GHCND:US1MNWG0168",
      "elevationUnit": "METERS",
      "longitude": -92.97415
    },
    {
      "elevation": 300.8,
      "mindate": "2023-06-02",
      "maxdate": "2025-01-07",
      "latitude": 45.058337,
      "name": "BIRCHWOOD VILLAGE 0.3 ESE, MN US",
      "datacoverage": 0.9819,
      "id": "GHCND:US1MNWG0169",
      "elevationUnit": "METERS",
      "longitude": -92.971012
    },
    {
      "elevation": 273.4,
      "mindate": "2023-03-27",
      "maxdate": "2024-11-19",
      "latitude": 45.103215,
      "name": "STILLWATER 4.2 NE, MN US",
      "datacoverage": 0.1821,
      "id": "GHCND:US1MNWG0177",
      "elevationUnit": "METERS",
      "longitude": -92.772039
    },
    {
      "elevation": 294.1,
      "mindate": "2023-08-16",
      "maxdate": "2024-09-19",
      "latitude": 45.112464,
      "name": "GRANT 2.8 NE, MN US",
      "datacoverage": 0.5761,
      "id": "GHCND:US1MNWG0182",
      "elevationUnit": "METERS",
      "longitude": -92.870735
    },
    {
      "elevation": 305.4,
      "mindate": "2023-09-01",
      "maxdate": "2025-01-31",
      "latitude": 44.93718,
      "name": "WOODBURY 3.2 NE, MN US",
      "datacoverage": 0.997,
      "id": "GHCND:US1MNWG0183",
      "elevationUnit": "METERS",
      "longitude": -92.87448
    },
    {
      "elevation": 246,
      "mindate": "2023-12-06",
      "maxdate": "2025-03-04",
      "latitude": 44.82488,
      "name": "COTTAGE GROVE 1.9 WNW, MN US",
      "datacoverage": 0.7253,
      "id": "GHCND:US1MNWG0186",
      "elevationUnit": "METERS",
      "longitude": -92.96433
    },
    {
      "elevation": 316.1,
      "mindate": "2024-03-18",
      "maxdate": "2025-03-07",
      "latitude": 44.92075,
      "name": "WOODBURY 1.6 NW, MN US",
      "datacoverage": 0.8614,
      "id": "GHCND:US1MNWG0187",
      "elevationUnit": "METERS",
      "longitude": -92.948389
    },
    {
      "elevation": 286.5,
      "mindate": "2024-04-15",
      "maxdate": "2024-11-20",
      "latitude": 45.0229,
      "name": "LAKE ELMO 2.2 NNE, MN US",
      "datacoverage": 0.9925,
      "id": "GHCND:US1MNWG0195",
      "elevationUnit": "METERS",
      "longitude": -92.88454
    },
    {
      "elevation": 305.4,
      "mindate": "2024-04-16",
      "maxdate": "2024-11-27",
      "latitude": 45.237785,
      "name": "SCANDIA 2.5 ESE, MN US",
      "datacoverage": 0.8271,
      "id": "GHCND:US1MNWG0198",
      "elevationUnit": "METERS",
      "longitude": -92.781523
    },
    {
      "elevation": 296.3,
      "mindate": "2024-04-06",
      "maxdate": "2025-02-01",
      "latitude": 45.110058,
      "name": "DELLWOOD 0.8 NNW, MN US",
      "datacoverage": 0.7815,
      "id": "GHCND:US1MNWG0202",
      "elevationUnit": "METERS",
      "longitude": -92.970956
    },
    {
      "elevation": 285.6,
      "mindate": "2024-04-17",
      "maxdate": "2024-10-25",
      "latitude": 44.91331,
      "name": "WOODBURY 1.5 ENE, MN US",
      "datacoverage": 0.9898,
      "id": "GHCND:US1MNWG0205",
      "elevationUnit": "METERS",
      "longitude": -92.89495
    },
    {
      "elevation": 294.4,
      "mindate": "2024-04-21",
      "maxdate": "2024-11-03",
      "latitude": 45.135632,
      "name": "HUGO 2.2 SSW, MN US",
      "datacoverage": 0.7513,
      "id": "GHCND:US1MNWG0206",
      "elevationUnit": "METERS",
      "longitude": -92.9701077
    },
    {
      "elevation": 302.7,
      "mindate": "2024-04-26",
      "maxdate": "2025-03-07",
      "latitude": 45.2007152,
      "name": "MARINE ON SAINT CROIX 2.2 W, MN US",
      "datacoverage": 1,
      "id": "GHCND:US1MNWG0207",
      "elevationUnit": "METERS",
      "longitude": -92.8246577
    },
    {
      "elevation": 271.3,
      "mindate": "2024-03-26",
      "maxdate": "2025-03-07",
      "latitude": 45.05685,
      "name": "STILLWATER 0.1 E, MN US",
      "datacoverage": 0.4553,
      "id": "GHCND:US1MNWG0210",
      "elevationUnit": "METERS",
      "longitude": -92.8257
    },
    {
      "elevation": 295.4,
      "mindate": "2024-04-01",
      "maxdate": "2024-11-14",
      "latitude": 45.0285929,
      "name": "LAKE ELMO 3.3 NW, MN US",
      "datacoverage": 1,
      "id": "GHCND:US1MNWG0211",
      "elevationUnit": "METERS",
      "longitude": -92.9500579
    },
    {
      "elevation": 321,
      "mindate": "2024-04-29",
      "maxdate": "2024-12-09",
      "latitude": 44.989609,
      "name": "OAKDALE 0.1 N, MN US",
      "datacoverage": 0.9956,
      "id": "GHCND:US1MNWG0216",
      "elevationUnit": "METERS",
      "longitude": -92.963997
    },
    {
      "elevation": 292.9,
      "mindate": "2024-07-01",
      "maxdate": "2025-03-07",
      "latitude": 44.940971,
      "name": "WOODBURY 2.4 N, MN US",
      "datacoverage": 0.856,
      "id": "GHCND:US1MNWG0217",
      "elevationUnit": "METERS",
      "longitude": -92.924278
    },
    {
      "elevation": 286.8,
      "mindate": "2010-03-01",
      "maxdate": "2011-10-03",
      "latitude": 46.436566,
      "name": "KENT 0.2 SW, MN US",
      "datacoverage": 0.998,
      "id": "GHCND:US1MNWK0001",
      "elevationUnit": "METERS",
      "longitude": -96.684669
    },
    {
      "elevation": 299.3,
      "mindate": "2011-01-01",
      "maxdate": "2016-02-19",
      "latitude": 46.095231,
      "name": "CAMPBELL 0.2 SSW, MN US",
      "datacoverage": 0.468,
      "id": "GHCND:US1MNWK0002",
      "elevationUnit": "METERS",
      "longitude": -96.406357
    },
    {
      "elevation": 293.2,
      "mindate": "2011-05-01",
      "maxdate": "2015-05-15",
      "latitude": 46.2784936,
      "name": "BRECKENRIDGE 0.9 NNW, MN US",
      "datacoverage": 1,
      "id": "GHCND:US1MNWK0003",
      "elevationUnit": "METERS",
      "longitude": -96.592854
    },
    {
      "elevation": 285.3,
      "mindate": "2018-05-24",
      "maxdate": "2025-03-07",
      "latitude": 46.5692,
      "name": "WOLVERTON 1.1 ENE, MN US",
      "datacoverage": 0.9878,
      "id": "GHCND:US1MNWK0005",
      "elevationUnit": "METERS",
      "longitude": -96.7154
    },
    {
      "elevation": 301.1,
      "mindate": "2023-09-03",
      "maxdate": "2025-02-08",
      "latitude": 46.50806,
      "name": "ROTHSAY 9.1 WNW, MN US",
      "datacoverage": 0.2324,
      "id": "GHCND:US1MNWK0007",
      "elevationUnit": "METERS",
      "longitude": -96.46583
    },
    {
      "elevation": 205.4,
      "mindate": "2010-11-01",
      "maxdate": "2019-10-22",
      "latitude": 44.017142,
      "name": "WINONA 3.8 SE, MN US",
      "datacoverage": 0.9848,
      "id": "GHCND:US1MNWN0002",
      "elevationUnit": "METERS",
      "longitude": -91.609815
    },
    {
      "elevation": 372.2,
      "mindate": "2011-03-01",
      "maxdate": "2025-03-06",
      "latitude": 43.98583333,
      "name": "LEWISTON 0.2 NW, MN US",
      "datacoverage": 0.9993,
      "id": "GHCND:US1MNWN0003",
      "elevationUnit": "METERS",
      "longitude": -91.87194444
    },
    {
      "elevation": 255.7,
      "mindate": "2010-04-01",
      "maxdate": "2012-10-26",
      "latitude": 44.115016,
      "name": "ROLLINGSTONE 1.8 NW, MN US",
      "datacoverage": 0.5153,
      "id": "GHCND:US1MNWN0004",
      "elevationUnit": "METERS",
      "longitude": -91.847341
    },
    {
      "elevation": 226.2,
      "mindate": "2011-03-01",
      "maxdate": "2024-11-22",
      "latitude": 44.030285,
      "name": "WINONA 5.1 WSW, MN US",
      "datacoverage": 0.6717,
      "id": "GHCND:US1MNWN0005",
      "elevationUnit": "METERS",
      "longitude": -91.768403
    },
    {
      "elevation": 229.8,
      "mindate": "2010-07-01",
      "maxdate": "2024-11-27",
      "latitude": 44.025866,
      "name": "STOCKTON 0.1 SSE, MN US",
      "datacoverage": 0.6229,
      "id": "GHCND:US1MNWN0006",
      "elevationUnit": "METERS",
      "longitude": -91.768966
    },
    {
      "elevation": 288,
      "mindate": "2011-04-01",
      "maxdate": "2015-08-30",
      "latitude": 43.89335,
      "name": "RUSHFORD 6.3 NNE, MN US",
      "datacoverage": 0.8675,
      "id": "GHCND:US1MNWN0007",
      "elevationUnit": "METERS",
      "longitude": -91.693282
    },
    {
      "elevation": 209.1,
      "mindate": "2017-03-29",
      "maxdate": "2024-09-23",
      "latitude": 44.0825,
      "name": "MINNESOTA CITY 1.1 SE, MN US",
      "datacoverage": 0.1849,
      "id": "GHCND:US1MNWN0009",
      "elevationUnit": "METERS",
      "longitude": -91.7338
    },
    {
      "elevation": 361.5,
      "mindate": "2017-10-22",
      "maxdate": "2022-06-16",
      "latitude": 44.033756,
      "name": "WINONA 1.3 SSW, MN US",
      "datacoverage": 0.8405,
      "id": "GHCND:US1MNWN0011",
      "elevationUnit": "METERS",
      "longitude": -91.679534
    },
    {
      "elevation": 206.3,
      "mindate": "2019-05-16",
      "maxdate": "2024-10-31",
      "latitude": 43.989062,
      "name": "WINONA 12.0 ESE, MN US",
      "datacoverage": 0.9819,
      "id": "GHCND:US1MNWN0013",
      "elevationUnit": "METERS",
      "longitude": -91.442944
    },
    {
      "elevation": 243.2,
      "mindate": "2020-06-01",
      "maxdate": "2023-08-11",
      "latitude": 44.0282907,
      "name": "STOCKTON 1.2 W, MN US",
      "datacoverage": 0.7706,
      "id": "GHCND:US1MNWN0019",
      "elevationUnit": "METERS",
      "longitude": -91.7933494
    },
    {
      "elevation": 200.9,
      "mindate": "2021-05-12",
      "maxdate": "2025-03-06",
      "latitude": 44.04219,
      "name": "WINONA 2.0 ESE, MN US",
      "datacoverage": 0.9986,
      "id": "GHCND:US1MNWN0021",
      "elevationUnit": "METERS",
      "longitude": -91.63064
    },
    {
      "elevation": 200.3,
      "mindate": "2021-05-27",
      "maxdate": "2025-03-07",
      "latitude": 44.043389,
      "name": "WINONA 1.9 ESE, MN US",
      "datacoverage": 0.8052,
      "id": "GHCND:US1MNWN0023",
      "elevationUnit": "METERS",
      "longitude": -91.633245
    },
    {
      "elevation": 265.2,
      "mindate": "2021-06-24",
      "maxdate": "2025-03-07",
      "latitude": 43.87973,
      "name": "LA CRESCENT 4.0 NNW, MN US",
      "datacoverage": 0.9986,
      "id": "GHCND:US1MNWN0024",
      "elevationUnit": "METERS",
      "longitude": -91.340246
    },
    {
      "elevation": 365.8,
      "mindate": "2022-04-01",
      "maxdate": "2024-12-02",
      "latitude": 44.1784338,
      "name": "MINNEISKA 1.1 SW, MN US",
      "datacoverage": 0.3717,
      "id": "GHCND:US1MNWN0026",
      "elevationUnit": "METERS",
      "longitude": -91.8831737
    },
    {
      "elevation": 237.7,
      "mindate": "2022-04-13",
      "maxdate": "2024-11-06",
      "latitude": 43.86208,
      "name": "LEWISTON 9.1 SSE, MN US",
      "datacoverage": 0.1672,
      "id": "GHCND:US1MNWN0027",
      "elevationUnit": "METERS",
      "longitude": -91.7998
    },
    {
      "elevation": 343.8,
      "mindate": "2022-05-26",
      "maxdate": "2023-11-21",
      "latitude": 43.9697821,
      "name": "SAINT CHARLES 0.4 W, MN US",
      "datacoverage": 0.998,
      "id": "GHCND:US1MNWN0029",
      "elevationUnit": "METERS",
      "longitude": -92.0666455
    },
    {
      "elevation": 355.7,
      "mindate": "2023-03-10",
      "maxdate": "2025-03-06",
      "latitude": 44.07365,
      "name": "ALTURA 0.7 NNE, MN US",
      "datacoverage": 0.2885,
      "id": "GHCND:US1MNWN0031",
      "elevationUnit": "METERS",
      "longitude": -91.93728
    },
    {
      "elevation": 258.8,
      "mindate": "2004-06-23",
      "maxdate": "2025-03-07",
      "latitude": 43.9979,
      "name": "WINONA 6.9 ESE, MN US",
      "datacoverage": 0.9566,
      "id": "GHCND:US1MNWN0033",
      "elevationUnit": "METERS",
      "longitude": -91.5513
    },
    {
      "elevation": 299.3,
      "mindate": "2010-01-01",
      "maxdate": "2012-05-24",
      "latitude": 45.096944,
      "name": "ROCKFORD 1.2 WNW, MN US",
      "datacoverage": 0.8408,
      "id": "GHCND:US1MNWR0006",
      "elevationUnit": "METERS",
      "longitude": -93.763611
    },
    {
      "elevation": 292.3,
      "mindate": "2010-04-01",
      "maxdate": "2025-03-07",
      "latitude": 45.201224,
      "name": "SAINT MICHAEL 1.3 E, MN US",
      "datacoverage": 0.9998,
      "id": "GHCND:US1MNWR0008",
      "elevationUnit": "METERS",
      "longitude": -93.665851
    },
    {
      "elevation": 292.9,
      "mindate": "2011-05-01",
      "maxdate": "2018-10-31",
      "latitude": 45.23944,
      "name": "ALBERTVILLE 0.3 NW, MN US",
      "datacoverage": 0.6291,
      "id": "GHCND:US1MNWR0011",
      "elevationUnit": "METERS",
      "longitude": -93.666874
    },
    {
      "elevation": 285,
      "mindate": "2011-04-01",
      "maxdate": "2015-11-19",
      "latitude": 45.044727,
      "name": "MONTROSE 1.6 SSE, MN US",
      "datacoverage": 0.7319,
      "id": "GHCND:US1MNWR0013",
      "elevationUnit": "METERS",
      "longitude": -93.910654
    },
    {
      "elevation": 281,
      "mindate": "2011-04-01",
      "maxdate": "2023-09-30",
      "latitude": 45.339169,
      "name": "MONTICELLO 6.4 ENE 45, MN US",
      "datacoverage": 0.6178,
      "id": "GHCND:US1MNWR0015",
      "elevationUnit": "METERS",
      "longitude": -93.680585
    },
    {
      "elevation": 318.2,
      "mindate": "2012-04-01",
      "maxdate": "2025-03-06",
      "latitude": 45.1031455993652,
      "name": "ROCKFORD 1.0 NE, MN US",
      "datacoverage": 0.9993,
      "id": "GHCND:US1MNWR0019",
      "elevationUnit": "METERS",
      "longitude": -93.7336807250977
    },
    {
      "elevation": 319.1,
      "mindate": "2012-04-01",
      "maxdate": "2024-10-31",
      "latitude": 45.228966,
      "name": "MAPLE LAKE 0.5 SE, MN US",
      "datacoverage": 0.7956,
      "id": "GHCND:US1MNWR0020",
      "elevationUnit": "METERS",
      "longitude": -93.99852
    },
    {
      "elevation": 863.5,
      "mindate": "2014-06-01",
      "maxdate": "2025-03-04",
      "latitude": 45.208202,
      "name": "SAINT MICHAEL 2.0 ENE, MN US",
      "datacoverage": 0.9994,
      "id": "GHCND:US1MNWR0025",
      "elevationUnit": "METERS",
      "longitude": -93.652833
    },
    {
      "elevation": 307.2,
      "mindate": "2015-05-01",
      "maxdate": "2025-03-06",
      "latitude": 45.1840667724609,
      "name": "BUFFALO 0.5 NW, MN US",
      "datacoverage": 0.9965,
      "id": "GHCND:US1MNWR0029",
      "elevationUnit": "METERS",
      "longitude": -93.8718032836914
    },
    {
      "elevation": 301.1,
      "mindate": "2016-03-21",
      "maxdate": "2024-10-25",
      "latitude": 45.175283,
      "name": "SAINT MICHAEL 2.7 SW, MN US",
      "datacoverage": 0.1671,
      "id": "GHCND:US1MNWR0031",
      "elevationUnit": "METERS",
      "longitude": -93.733767
    },
    {
      "elevation": 294.4,
      "mindate": "2016-12-08",
      "maxdate": "2025-02-08",
      "latitude": 45.253598,
      "name": "OTSEGO 2.1 WSW, MN US",
      "datacoverage": 0.5635,
      "id": "GHCND:US1MNWR0035",
      "elevationUnit": "METERS",
      "longitude": -93.659205
    },
    {
      "elevation": 292,
      "mindate": "2016-12-17",
      "maxdate": "2025-01-21",
      "latitude": 45.3704071044922,
      "name": "CLEARWATER 5.0 SE, MN US",
      "datacoverage": 0.0615,
      "id": "GHCND:US1MNWR0036",
      "elevationUnit": "METERS",
      "longitude": -93.9872665405273
    },
    {
      "elevation": 318.2,
      "mindate": "2017-03-29",
      "maxdate": "2024-10-25",
      "latitude": 45.206684,
      "name": "BUFFALO 2.4 NE, MN US",
      "datacoverage": 0.3396,
      "id": "GHCND:US1MNWR0037",
      "elevationUnit": "METERS",
      "longitude": -93.833246
    },
    {
      "elevation": 296.6,
      "mindate": "2017-01-01",
      "maxdate": "2019-01-24",
      "latitude": 45.3241,
      "name": "MONTICELLO 4.8 WNW, MN US",
      "datacoverage": 1,
      "id": "GHCND:US1MNWR0038",
      "elevationUnit": "METERS",
      "longitude": -93.8913
    },
    {
      "elevation": 309.7,
      "mindate": "2017-03-21",
      "maxdate": "2023-01-22",
      "latitude": 45.34795,
      "name": "CLEARWATER 5.4 SSE, MN US",
      "datacoverage": 0.9996,
      "id": "GHCND:US1MNWR0040",
      "elevationUnit": "METERS",
      "longitude": -94.03374
    }
  ]
}
